{
  "kind": "ref",
  "body_type": "[]sdk.Log",
  "body": [
    {
      "timestamp": "2025-08-06T21:47:57.755496-04:00",
      "message": "/opt/homebrew/bin/infisical",
      "attributes": {
        "col": "30",
        "filename": "sdk/0.3.0/host.star",
        "line": "45",
        "thread": "_destroy"
      },
      "stream": 0
    },
    {
      "timestamp": "2025-08-06T21:47:58.343291-04:00",
      "message": "/opt/homebrew/bin/terraform",
      "attributes": {
        "col": "30",
        "filename": "sdk/0.3.0/host.star",
        "line": "45",
        "thread": "_destroy"
      },
      "stream": 0
    },
    {
      "timestamp": "2025-08-06T21:47:58.349089-04:00",
      "message": "/Users/tom/src/github.com/ocuroot/vps-demo/vps",
      "attributes": {
        "col": "30",
        "filename": "sdk/0.3.0/host.star",
        "line": "45",
        "thread": "_destroy"
      },
      "stream": 0
    },
    {
      "timestamp": "2025-08-06T21:47:59.697637-04:00",
      "message": "- Fetching hashicorp/google 6.14.1 for linux_amd64...",
      "attributes": {
        "col": "30",
        "filename": "sdk/0.3.0/host.star",
        "line": "45",
        "thread": "_destroy"
      },
      "stream": 0
    },
    {
      "timestamp": "2025-08-06T21:48:01.135333-04:00",
      "message": "- Retrieved hashicorp/google 6.14.1 for linux_amd64 (signed by HashiCorp)",
      "attributes": {
        "col": "30",
        "filename": "sdk/0.3.0/host.star",
        "line": "45",
        "thread": "_destroy"
      },
      "stream": 0
    },
    {
      "timestamp": "2025-08-06T21:48:01.676734-04:00",
      "message": "- Fetching digitalocean/digitalocean 2.36.0 for linux_amd64...",
      "attributes": {
        "col": "30",
        "filename": "sdk/0.3.0/host.star",
        "line": "45",
        "thread": "_destroy"
      },
      "stream": 0
    },
    {
      "timestamp": "2025-08-06T21:48:02.369303-04:00",
      "message": "- Retrieved digitalocean/digitalocean 2.36.0 for linux_amd64 (signed by a HashiCorp partner, key ID \u001b[0m\u001b[1mF82037E524B9C0E8\u001b[0m\u001b[0m)",
      "attributes": {
        "col": "30",
        "filename": "sdk/0.3.0/host.star",
        "line": "45",
        "thread": "_destroy"
      },
      "stream": 0
    },
    {
      "timestamp": "2025-08-06T21:48:02.549617-04:00",
      "message": "- Fetching hashicorp/tls 4.1.0 for linux_amd64...",
      "attributes": {
        "col": "30",
        "filename": "sdk/0.3.0/host.star",
        "line": "45",
        "thread": "_destroy"
      },
      "stream": 0
    },
    {
      "timestamp": "2025-08-06T21:48:02.996994-04:00",
      "message": "- Retrieved hashicorp/tls 4.1.0 for linux_amd64 (signed by HashiCorp)",
      "attributes": {
        "col": "30",
        "filename": "sdk/0.3.0/host.star",
        "line": "45",
        "thread": "_destroy"
      },
      "stream": 0
    },
    {
      "timestamp": "2025-08-06T21:48:02.997065-04:00",
      "message": "- Obtained hashicorp/google checksums for linux_amd64; All checksums for this platform were already tracked in the lock file",
      "attributes": {
        "col": "30",
        "filename": "sdk/0.3.0/host.star",
        "line": "45",
        "thread": "_destroy"
      },
      "stream": 0
    },
    {
      "timestamp": "2025-08-06T21:48:02.997097-04:00",
      "message": "- Obtained digitalocean/digitalocean checksums for linux_amd64; All checksums for this platform were already tracked in the lock file",
      "attributes": {
        "col": "30",
        "filename": "sdk/0.3.0/host.star",
        "line": "45",
        "thread": "_destroy"
      },
      "stream": 0
    },
    {
      "timestamp": "2025-08-06T21:48:02.997131-04:00",
      "message": "- Obtained hashicorp/tls checksums for linux_amd64; All checksums for this platform were already tracked in the lock file",
      "attributes": {
        "col": "30",
        "filename": "sdk/0.3.0/host.star",
        "line": "45",
        "thread": "_destroy"
      },
      "stream": 0
    },
    {
      "timestamp": "2025-08-06T21:48:02.997726-04:00",
      "message": "",
      "attributes": {
        "col": "30",
        "filename": "sdk/0.3.0/host.star",
        "line": "45",
        "thread": "_destroy"
      },
      "stream": 0
    },
    {
      "timestamp": "2025-08-06T21:48:02.997762-04:00",
      "message": "\u001b[1m\u001b[32mSuccess!\u001b[0m \u001b[1mTerraform has validated the lock file and found no need for changes.\u001b[0m\u001b[0m",
      "attributes": {
        "col": "30",
        "filename": "sdk/0.3.0/host.star",
        "line": "45",
        "thread": "_destroy"
      },
      "stream": 0
    },
    {
      "timestamp": "2025-08-06T21:48:03.032354-04:00",
      "message": "\u001b[0m\u001b[1mInitializing the backend...\u001b[0m",
      "attributes": {
        "col": "30",
        "filename": "sdk/0.3.0/host.star",
        "line": "45",
        "thread": "_destroy"
      },
      "stream": 0
    },
    {
      "timestamp": "2025-08-06T21:48:03.502081-04:00",
      "message": "\u001b[0m\u001b[32m",
      "attributes": {
        "col": "30",
        "filename": "sdk/0.3.0/host.star",
        "line": "45",
        "thread": "_destroy"
      },
      "stream": 0
    },
    {
      "timestamp": "2025-08-06T21:48:03.50252-04:00",
      "message": "Successfully configured the backend \"gcs\"! Terraform will automatically",
      "attributes": {
        "col": "30",
        "filename": "sdk/0.3.0/host.star",
        "line": "45",
        "thread": "_destroy"
      },
      "stream": 0
    },
    {
      "timestamp": "2025-08-06T21:48:03.502632-04:00",
      "message": "use this backend unless the backend configuration changes.\u001b[0m",
      "attributes": {
        "col": "30",
        "filename": "sdk/0.3.0/host.star",
        "line": "45",
        "thread": "_destroy"
      },
      "stream": 0
    },
    {
      "timestamp": "2025-08-06T21:48:03.938962-04:00",
      "message": "\u001b[0m\u001b[1mInitializing provider plugins...\u001b[0m",
      "attributes": {
        "col": "30",
        "filename": "sdk/0.3.0/host.star",
        "line": "45",
        "thread": "_destroy"
      },
      "stream": 0
    },
    {
      "timestamp": "2025-08-06T21:48:03.939187-04:00",
      "message": "- Reusing previous version of hashicorp/tls from the dependency lock file",
      "attributes": {
        "col": "30",
        "filename": "sdk/0.3.0/host.star",
        "line": "45",
        "thread": "_destroy"
      },
      "stream": 0
    },
    {
      "timestamp": "2025-08-06T21:48:04.107485-04:00",
      "message": "- Reusing previous version of digitalocean/digitalocean from the dependency lock file",
      "attributes": {
        "col": "30",
        "filename": "sdk/0.3.0/host.star",
        "line": "45",
        "thread": "_destroy"
      },
      "stream": 0
    },
    {
      "timestamp": "2025-08-06T21:48:04.191109-04:00",
      "message": "- Reusing previous version of hashicorp/google from the dependency lock file",
      "attributes": {
        "col": "30",
        "filename": "sdk/0.3.0/host.star",
        "line": "45",
        "thread": "_destroy"
      },
      "stream": 0
    },
    {
      "timestamp": "2025-08-06T21:48:04.306959-04:00",
      "message": "- Using previously-installed hashicorp/tls v4.1.0",
      "attributes": {
        "col": "30",
        "filename": "sdk/0.3.0/host.star",
        "line": "45",
        "thread": "_destroy"
      },
      "stream": 0
    },
    {
      "timestamp": "2025-08-06T21:48:04.326658-04:00",
      "message": "- Using previously-installed digitalocean/digitalocean v2.36.0",
      "attributes": {
        "col": "30",
        "filename": "sdk/0.3.0/host.star",
        "line": "45",
        "thread": "_destroy"
      },
      "stream": 0
    },
    {
      "timestamp": "2025-08-06T21:48:04.385588-04:00",
      "message": "- Using previously-installed hashicorp/google v6.14.1",
      "attributes": {
        "col": "30",
        "filename": "sdk/0.3.0/host.star",
        "line": "45",
        "thread": "_destroy"
      },
      "stream": 0
    },
    {
      "timestamp": "2025-08-06T21:48:04.385661-04:00",
      "message": "",
      "attributes": {
        "col": "30",
        "filename": "sdk/0.3.0/host.star",
        "line": "45",
        "thread": "_destroy"
      },
      "stream": 0
    },
    {
      "timestamp": "2025-08-06T21:48:04.385685-04:00",
      "message": "\u001b[0m\u001b[1m\u001b[32mTerraform has been successfully initialized!\u001b[0m\u001b[32m\u001b[0m",
      "attributes": {
        "col": "30",
        "filename": "sdk/0.3.0/host.star",
        "line": "45",
        "thread": "_destroy"
      },
      "stream": 0
    },
    {
      "timestamp": "2025-08-06T21:48:04.385757-04:00",
      "message": "\u001b[0m\u001b[32m",
      "attributes": {
        "col": "30",
        "filename": "sdk/0.3.0/host.star",
        "line": "45",
        "thread": "_destroy"
      },
      "stream": 0
    },
    {
      "timestamp": "2025-08-06T21:48:04.38579-04:00",
      "message": "You may now begin working with Terraform. Try running \"terraform plan\" to see",
      "attributes": {
        "col": "30",
        "filename": "sdk/0.3.0/host.star",
        "line": "45",
        "thread": "_destroy"
      },
      "stream": 0
    },
    {
      "timestamp": "2025-08-06T21:48:04.385814-04:00",
      "message": "any changes that are required for your infrastructure. All Terraform commands",
      "attributes": {
        "col": "30",
        "filename": "sdk/0.3.0/host.star",
        "line": "45",
        "thread": "_destroy"
      },
      "stream": 0
    },
    {
      "timestamp": "2025-08-06T21:48:04.385837-04:00",
      "message": "should now work.",
      "attributes": {
        "col": "30",
        "filename": "sdk/0.3.0/host.star",
        "line": "45",
        "thread": "_destroy"
      },
      "stream": 0
    },
    {
      "timestamp": "2025-08-06T21:48:04.38586-04:00",
      "message": "",
      "attributes": {
        "col": "30",
        "filename": "sdk/0.3.0/host.star",
        "line": "45",
        "thread": "_destroy"
      },
      "stream": 0
    },
    {
      "timestamp": "2025-08-06T21:48:04.385886-04:00",
      "message": "If you ever set or change modules or backend configuration for Terraform,",
      "attributes": {
        "col": "30",
        "filename": "sdk/0.3.0/host.star",
        "line": "45",
        "thread": "_destroy"
      },
      "stream": 0
    },
    {
      "timestamp": "2025-08-06T21:48:04.385914-04:00",
      "message": "rerun this command to reinitialize your working directory. If you forget, other",
      "attributes": {
        "col": "30",
        "filename": "sdk/0.3.0/host.star",
        "line": "45",
        "thread": "_destroy"
      },
      "stream": 0
    },
    {
      "timestamp": "2025-08-06T21:48:04.385938-04:00",
      "message": "commands will detect it and remind you to do so if necessary.\u001b[0m",
      "attributes": {
        "col": "30",
        "filename": "sdk/0.3.0/host.star",
        "line": "45",
        "thread": "_destroy"
      },
      "stream": 0
    },
    {
      "timestamp": "2025-08-06T21:48:05.723807-04:00",
      "message": "Acquiring state lock. This may take a few moments...",
      "attributes": {
        "col": "30",
        "filename": "sdk/0.3.0/host.star",
        "line": "45",
        "thread": "_destroy"
      },
      "stream": 0
    },
    {
      "timestamp": "2025-08-06T21:48:06.273055-04:00",
      "message": "\u001b[0m\u001b[1mtls_private_key.vps: Refreshing state... [id=2762a2f4a191df81ca88941ce1ef18994726db11]\u001b[0m",
      "attributes": {
        "col": "30",
        "filename": "sdk/0.3.0/host.star",
        "line": "45",
        "thread": "_destroy"
      },
      "stream": 0
    },
    {
      "timestamp": "2025-08-06T21:48:06.280424-04:00",
      "message": "\u001b[0m\u001b[1mdigitalocean_ssh_key.default: Refreshing state... [id=49770501]\u001b[0m",
      "attributes": {
        "col": "30",
        "filename": "sdk/0.3.0/host.star",
        "line": "45",
        "thread": "_destroy"
      },
      "stream": 0
    },
    {
      "timestamp": "2025-08-06T21:48:06.657081-04:00",
      "message": "\u001b[0m\u001b[1mdigitalocean_droplet.vps: Refreshing state... [id=512034846]\u001b[0m",
      "attributes": {
        "col": "30",
        "filename": "sdk/0.3.0/host.star",
        "line": "45",
        "thread": "_destroy"
      },
      "stream": 0
    },
    {
      "timestamp": "2025-08-06T21:48:07.206411-04:00",
      "message": "",
      "attributes": {
        "col": "30",
        "filename": "sdk/0.3.0/host.star",
        "line": "45",
        "thread": "_destroy"
      },
      "stream": 0
    },
    {
      "timestamp": "2025-08-06T21:48:07.206469-04:00",
      "message": "Terraform used the selected providers to generate the following execution",
      "attributes": {
        "col": "30",
        "filename": "sdk/0.3.0/host.star",
        "line": "45",
        "thread": "_destroy"
      },
      "stream": 0
    },
    {
      "timestamp": "2025-08-06T21:48:07.206494-04:00",
      "message": "plan. Resource actions are indicated with the following symbols:",
      "attributes": {
        "col": "30",
        "filename": "sdk/0.3.0/host.star",
        "line": "45",
        "thread": "_destroy"
      },
      "stream": 0
    },
    {
      "timestamp": "2025-08-06T21:48:07.206517-04:00",
      "message": "  \u001b[31m-\u001b[0m destroy\u001b[0m",
      "attributes": {
        "col": "30",
        "filename": "sdk/0.3.0/host.star",
        "line": "45",
        "thread": "_destroy"
      },
      "stream": 0
    },
    {
      "timestamp": "2025-08-06T21:48:07.20655-04:00",
      "message": "",
      "attributes": {
        "col": "30",
        "filename": "sdk/0.3.0/host.star",
        "line": "45",
        "thread": "_destroy"
      },
      "stream": 0
    },
    {
      "timestamp": "2025-08-06T21:48:07.206627-04:00",
      "message": "Terraform will perform the following actions:",
      "attributes": {
        "col": "30",
        "filename": "sdk/0.3.0/host.star",
        "line": "45",
        "thread": "_destroy"
      },
      "stream": 0
    },
    {
      "timestamp": "2025-08-06T21:48:07.206677-04:00",
      "message": "",
      "attributes": {
        "col": "30",
        "filename": "sdk/0.3.0/host.star",
        "line": "45",
        "thread": "_destroy"
      },
      "stream": 0
    },
    {
      "timestamp": "2025-08-06T21:48:07.206702-04:00",
      "message": "\u001b[1m  # digitalocean_droplet.vps\u001b[0m will be \u001b[1m\u001b[31mdestroyed\u001b[0m",
      "attributes": {
        "col": "30",
        "filename": "sdk/0.3.0/host.star",
        "line": "45",
        "thread": "_destroy"
      },
      "stream": 0
    },
    {
      "timestamp": "2025-08-06T21:48:07.206727-04:00",
      "message": "\u001b[0m  \u001b[31m-\u001b[0m\u001b[0m resource \"digitalocean_droplet\" \"vps\" {",
      "attributes": {
        "col": "30",
        "filename": "sdk/0.3.0/host.star",
        "line": "45",
        "thread": "_destroy"
      },
      "stream": 0
    },
    {
      "timestamp": "2025-08-06T21:48:07.206753-04:00",
      "message": "      \u001b[31m-\u001b[0m\u001b[0m backups              = false \u001b[90m-\u003e null\u001b[0m\u001b[0m",
      "attributes": {
        "col": "30",
        "filename": "sdk/0.3.0/host.star",
        "line": "45",
        "thread": "_destroy"
      },
      "stream": 0
    },
    {
      "timestamp": "2025-08-06T21:48:07.206778-04:00",
      "message": "      \u001b[31m-\u001b[0m\u001b[0m created_at           = \"2025-08-06T17:42:50Z\" \u001b[90m-\u003e null\u001b[0m\u001b[0m",
      "attributes": {
        "col": "30",
        "filename": "sdk/0.3.0/host.star",
        "line": "45",
        "thread": "_destroy"
      },
      "stream": 0
    },
    {
      "timestamp": "2025-08-06T21:48:07.206802-04:00",
      "message": "      \u001b[31m-\u001b[0m\u001b[0m disk                 = 25 \u001b[90m-\u003e null\u001b[0m\u001b[0m",
      "attributes": {
        "col": "30",
        "filename": "sdk/0.3.0/host.star",
        "line": "45",
        "thread": "_destroy"
      },
      "stream": 0
    },
    {
      "timestamp": "2025-08-06T21:48:07.206824-04:00",
      "message": "      \u001b[31m-\u001b[0m\u001b[0m graceful_shutdown    = false \u001b[90m-\u003e null\u001b[0m\u001b[0m",
      "attributes": {
        "col": "30",
        "filename": "sdk/0.3.0/host.star",
        "line": "45",
        "thread": "_destroy"
      },
      "stream": 0
    },
    {
      "timestamp": "2025-08-06T21:48:07.206849-04:00",
      "message": "      \u001b[31m-\u001b[0m\u001b[0m id                   = \"512034846\" \u001b[90m-\u003e null\u001b[0m\u001b[0m",
      "attributes": {
        "col": "30",
        "filename": "sdk/0.3.0/host.star",
        "line": "45",
        "thread": "_destroy"
      },
      "stream": 0
    },
    {
      "timestamp": "2025-08-06T21:48:07.206872-04:00",
      "message": "      \u001b[31m-\u001b[0m\u001b[0m image                = \"ubuntu-22-04-x64\" \u001b[90m-\u003e null\u001b[0m\u001b[0m",
      "attributes": {
        "col": "30",
        "filename": "sdk/0.3.0/host.star",
        "line": "45",
        "thread": "_destroy"
      },
      "stream": 0
    },
    {
      "timestamp": "2025-08-06T21:48:07.206895-04:00",
      "message": "      \u001b[31m-\u001b[0m\u001b[0m ipv4_address         = \"162.243.84.176\" \u001b[90m-\u003e null\u001b[0m\u001b[0m",
      "attributes": {
        "col": "30",
        "filename": "sdk/0.3.0/host.star",
        "line": "45",
        "thread": "_destroy"
      },
      "stream": 0
    },
    {
      "timestamp": "2025-08-06T21:48:07.206922-04:00",
      "message": "      \u001b[31m-\u001b[0m\u001b[0m ipv4_address_private = \"10.100.0.2\" \u001b[90m-\u003e null\u001b[0m\u001b[0m",
      "attributes": {
        "col": "30",
        "filename": "sdk/0.3.0/host.star",
        "line": "45",
        "thread": "_destroy"
      },
      "stream": 0
    },
    {
      "timestamp": "2025-08-06T21:48:07.206945-04:00",
      "message": "      \u001b[31m-\u001b[0m\u001b[0m ipv6                 = false \u001b[90m-\u003e null\u001b[0m\u001b[0m",
      "attributes": {
        "col": "30",
        "filename": "sdk/0.3.0/host.star",
        "line": "45",
        "thread": "_destroy"
      },
      "stream": 0
    },
    {
      "timestamp": "2025-08-06T21:48:07.206967-04:00",
      "message": "      \u001b[31m-\u001b[0m\u001b[0m locked               = false \u001b[90m-\u003e null\u001b[0m\u001b[0m",
      "attributes": {
        "col": "30",
        "filename": "sdk/0.3.0/host.star",
        "line": "45",
        "thread": "_destroy"
      },
      "stream": 0
    },
    {
      "timestamp": "2025-08-06T21:48:07.206993-04:00",
      "message": "      \u001b[31m-\u001b[0m\u001b[0m memory               = 1024 \u001b[90m-\u003e null\u001b[0m\u001b[0m",
      "attributes": {
        "col": "30",
        "filename": "sdk/0.3.0/host.star",
        "line": "45",
        "thread": "_destroy"
      },
      "stream": 0
    },
    {
      "timestamp": "2025-08-06T21:48:07.207016-04:00",
      "message": "      \u001b[31m-\u001b[0m\u001b[0m monitoring           = false \u001b[90m-\u003e null\u001b[0m\u001b[0m",
      "attributes": {
        "col": "30",
        "filename": "sdk/0.3.0/host.star",
        "line": "45",
        "thread": "_destroy"
      },
      "stream": 0
    },
    {
      "timestamp": "2025-08-06T21:48:07.207042-04:00",
      "message": "      \u001b[31m-\u001b[0m\u001b[0m name                 = \"vps-production\" \u001b[90m-\u003e null\u001b[0m\u001b[0m",
      "attributes": {
        "col": "30",
        "filename": "sdk/0.3.0/host.star",
        "line": "45",
        "thread": "_destroy"
      },
      "stream": 0
    },
    {
      "timestamp": "2025-08-06T21:48:07.207068-04:00",
      "message": "      \u001b[31m-\u001b[0m\u001b[0m price_hourly         = 0.00893 \u001b[90m-\u003e null\u001b[0m\u001b[0m",
      "attributes": {
        "col": "30",
        "filename": "sdk/0.3.0/host.star",
        "line": "45",
        "thread": "_destroy"
      },
      "stream": 0
    },
    {
      "timestamp": "2025-08-06T21:48:07.20709-04:00",
      "message": "      \u001b[31m-\u001b[0m\u001b[0m price_monthly        = 6 \u001b[90m-\u003e null\u001b[0m\u001b[0m",
      "attributes": {
        "col": "30",
        "filename": "sdk/0.3.0/host.star",
        "line": "45",
        "thread": "_destroy"
      },
      "stream": 0
    },
    {
      "timestamp": "2025-08-06T21:48:07.207116-04:00",
      "message": "      \u001b[31m-\u001b[0m\u001b[0m private_networking   = true \u001b[90m-\u003e null\u001b[0m\u001b[0m",
      "attributes": {
        "col": "30",
        "filename": "sdk/0.3.0/host.star",
        "line": "45",
        "thread": "_destroy"
      },
      "stream": 0
    },
    {
      "timestamp": "2025-08-06T21:48:07.20714-04:00",
      "message": "      \u001b[31m-\u001b[0m\u001b[0m region               = \"nyc2\" \u001b[90m-\u003e null\u001b[0m\u001b[0m",
      "attributes": {
        "col": "30",
        "filename": "sdk/0.3.0/host.star",
        "line": "45",
        "thread": "_destroy"
      },
      "stream": 0
    },
    {
      "timestamp": "2025-08-06T21:48:07.207163-04:00",
      "message": "      \u001b[31m-\u001b[0m\u001b[0m resize_disk          = true \u001b[90m-\u003e null\u001b[0m\u001b[0m",
      "attributes": {
        "col": "30",
        "filename": "sdk/0.3.0/host.star",
        "line": "45",
        "thread": "_destroy"
      },
      "stream": 0
    },
    {
      "timestamp": "2025-08-06T21:48:07.207186-04:00",
      "message": "      \u001b[31m-\u001b[0m\u001b[0m size                 = \"s-1vcpu-1gb\" \u001b[90m-\u003e null\u001b[0m\u001b[0m",
      "attributes": {
        "col": "30",
        "filename": "sdk/0.3.0/host.star",
        "line": "45",
        "thread": "_destroy"
      },
      "stream": 0
    },
    {
      "timestamp": "2025-08-06T21:48:07.207218-04:00",
      "message": "      \u001b[31m-\u001b[0m\u001b[0m ssh_keys             = [",
      "attributes": {
        "col": "30",
        "filename": "sdk/0.3.0/host.star",
        "line": "45",
        "thread": "_destroy"
      },
      "stream": 0
    },
    {
      "timestamp": "2025-08-06T21:48:07.20724-04:00",
      "message": "          \u001b[31m-\u001b[0m\u001b[0m \"49770501\",",
      "attributes": {
        "col": "30",
        "filename": "sdk/0.3.0/host.star",
        "line": "45",
        "thread": "_destroy"
      },
      "stream": 0
    },
    {
      "timestamp": "2025-08-06T21:48:07.207262-04:00",
      "message": "        ] \u001b[90m-\u003e null\u001b[0m\u001b[0m",
      "attributes": {
        "col": "30",
        "filename": "sdk/0.3.0/host.star",
        "line": "45",
        "thread": "_destroy"
      },
      "stream": 0
    },
    {
      "timestamp": "2025-08-06T21:48:07.207284-04:00",
      "message": "      \u001b[31m-\u001b[0m\u001b[0m status               = \"active\" \u001b[90m-\u003e null\u001b[0m\u001b[0m",
      "attributes": {
        "col": "30",
        "filename": "sdk/0.3.0/host.star",
        "line": "45",
        "thread": "_destroy"
      },
      "stream": 0
    },
    {
      "timestamp": "2025-08-06T21:48:07.207306-04:00",
      "message": "      \u001b[31m-\u001b[0m\u001b[0m tags                 = [] \u001b[90m-\u003e null\u001b[0m\u001b[0m",
      "attributes": {
        "col": "30",
        "filename": "sdk/0.3.0/host.star",
        "line": "45",
        "thread": "_destroy"
      },
      "stream": 0
    },
    {
      "timestamp": "2025-08-06T21:48:07.207329-04:00",
      "message": "      \u001b[31m-\u001b[0m\u001b[0m urn                  = \"do:droplet:512034846\" \u001b[90m-\u003e null\u001b[0m\u001b[0m",
      "attributes": {
        "col": "30",
        "filename": "sdk/0.3.0/host.star",
        "line": "45",
        "thread": "_destroy"
      },
      "stream": 0
    },
    {
      "timestamp": "2025-08-06T21:48:07.207352-04:00",
      "message": "      \u001b[31m-\u001b[0m\u001b[0m vcpus                = 1 \u001b[90m-\u003e null\u001b[0m\u001b[0m",
      "attributes": {
        "col": "30",
        "filename": "sdk/0.3.0/host.star",
        "line": "45",
        "thread": "_destroy"
      },
      "stream": 0
    },
    {
      "timestamp": "2025-08-06T21:48:07.207426-04:00",
      "message": "      \u001b[31m-\u001b[0m\u001b[0m volume_ids           = [] \u001b[90m-\u003e null\u001b[0m\u001b[0m",
      "attributes": {
        "col": "30",
        "filename": "sdk/0.3.0/host.star",
        "line": "45",
        "thread": "_destroy"
      },
      "stream": 0
    },
    {
      "timestamp": "2025-08-06T21:48:07.207478-04:00",
      "message": "      \u001b[31m-\u001b[0m\u001b[0m vpc_uuid             = \"2e15b6d3-778c-4a3d-8de5-9ee35fd7dd59\" \u001b[90m-\u003e null\u001b[0m\u001b[0m",
      "attributes": {
        "col": "30",
        "filename": "sdk/0.3.0/host.star",
        "line": "45",
        "thread": "_destroy"
      },
      "stream": 0
    },
    {
      "timestamp": "2025-08-06T21:48:07.207504-04:00",
      "message": "        \u001b[90m# (1 unchanged attribute hidden)\u001b[0m\u001b[0m",
      "attributes": {
        "col": "30",
        "filename": "sdk/0.3.0/host.star",
        "line": "45",
        "thread": "_destroy"
      },
      "stream": 0
    },
    {
      "timestamp": "2025-08-06T21:48:07.20753-04:00",
      "message": "    }",
      "attributes": {
        "col": "30",
        "filename": "sdk/0.3.0/host.star",
        "line": "45",
        "thread": "_destroy"
      },
      "stream": 0
    },
    {
      "timestamp": "2025-08-06T21:48:07.207551-04:00",
      "message": "",
      "attributes": {
        "col": "30",
        "filename": "sdk/0.3.0/host.star",
        "line": "45",
        "thread": "_destroy"
      },
      "stream": 0
    },
    {
      "timestamp": "2025-08-06T21:48:07.207573-04:00",
      "message": "\u001b[1m  # digitalocean_ssh_key.default\u001b[0m will be \u001b[1m\u001b[31mdestroyed\u001b[0m",
      "attributes": {
        "col": "30",
        "filename": "sdk/0.3.0/host.star",
        "line": "45",
        "thread": "_destroy"
      },
      "stream": 0
    },
    {
      "timestamp": "2025-08-06T21:48:07.207603-04:00",
      "message": "\u001b[0m  \u001b[31m-\u001b[0m\u001b[0m resource \"digitalocean_ssh_key\" \"default\" {",
      "attributes": {
        "col": "30",
        "filename": "sdk/0.3.0/host.star",
        "line": "45",
        "thread": "_destroy"
      },
      "stream": 0
    },
    {
      "timestamp": "2025-08-06T21:48:07.207625-04:00",
      "message": "      \u001b[31m-\u001b[0m\u001b[0m fingerprint = \"0a:95:68:24:e9:6c:16:c5:80:35:c0:5b:e3:de:41:dd\" \u001b[90m-\u003e null\u001b[0m\u001b[0m",
      "attributes": {
        "col": "30",
        "filename": "sdk/0.3.0/host.star",
        "line": "45",
        "thread": "_destroy"
      },
      "stream": 0
    },
    {
      "timestamp": "2025-08-06T21:48:07.20765-04:00",
      "message": "      \u001b[31m-\u001b[0m\u001b[0m id          = \"49770501\" \u001b[90m-\u003e null\u001b[0m\u001b[0m",
      "attributes": {
        "col": "30",
        "filename": "sdk/0.3.0/host.star",
        "line": "45",
        "thread": "_destroy"
      },
      "stream": 0
    },
    {
      "timestamp": "2025-08-06T21:48:07.207675-04:00",
      "message": "      \u001b[31m-\u001b[0m\u001b[0m name        = \"VPS demo production\" \u001b[90m-\u003e null\u001b[0m\u001b[0m",
      "attributes": {
        "col": "30",
        "filename": "sdk/0.3.0/host.star",
        "line": "45",
        "thread": "_destroy"
      },
      "stream": 0
    },
    {
      "timestamp": "2025-08-06T21:48:07.207697-04:00",
      "message": "      \u001b[31m-\u001b[0m\u001b[0m public_key  = \u003c\u003c-EOT",
      "attributes": {
        "col": "30",
        "filename": "sdk/0.3.0/host.star",
        "line": "45",
        "thread": "_destroy"
      },
      "stream": 0
    },
    {
      "timestamp": "2025-08-06T21:48:07.207719-04:00",
      "message": "            ssh-rsa AAAAB3NzaC1yc2EAAAADAQABAAACAQDcGu4ASieJhv9YkidDOahiwph1jwoJeYOuW2J/VTV2hrgRpR1Mb8V/6Gzc0As/HP6oVVqJzjekewy05O25ZdnximdarbSrnnAKGVnxyjSlyNxzOEqLhSZtp6cvC6t06AEaM4dj/JcpVwAApLY5JwQ3DPMMNpy73x08ZJdr3RXTOms7AICUB4TBmkbJSz2QojjPqdP95ocK5cJEnHF7GHSz7uH/V5Re2q9z3LPKunpoY0oUI2Tsg+JwIXqpiuydMHIdNzq1mNlmsstpMtp2X/eC38+0Ld61lP4bLUNuhtkzdSvwcIhm+1q0gt2XTS4NWkFEo3jDh42dCLT9L55f7mxMrrT4Crp1LrsoB5S7hefT/1u89iLTYVnMLaKCekhJUedEXyUBhUz3NUnuCUtS51eSnmZyKVctPhfhcxTSeYyZe8jF6LCTpaNkYyX638zLghC7QXz+nImU+JoAx3vAOfoCIvZPeX2YhLSTOePiNQ2YivoqOQ+fCIaPxLiO5VTXwUu8mc1BGdoEl/o0RZ0OIV1Ll30iB899Ik0l3KxVbmGc2TdrIPizpyX7O5TasYpm4mFteGBGYtwGDk/DY21+QzQbiYGSy/AGfYZWV3oN1xxr94tgDk4eyG5k2WhbamZeEGscQNySvZcd1yk8OBW+3j4xlLXSbhbqJPMgPXyOYzo7bQ==",
      "attributes": {
        "col": "30",
        "filename": "sdk/0.3.0/host.star",
        "line": "45",
        "thread": "_destroy"
      },
      "stream": 0
    },
    {
      "timestamp": "2025-08-06T21:48:07.20777-04:00",
      "message": "        EOT \u001b[90m-\u003e null\u001b[0m\u001b[0m",
      "attributes": {
        "col": "30",
        "filename": "sdk/0.3.0/host.star",
        "line": "45",
        "thread": "_destroy"
      },
      "stream": 0
    },
    {
      "timestamp": "2025-08-06T21:48:07.207799-04:00",
      "message": "    }",
      "attributes": {
        "col": "30",
        "filename": "sdk/0.3.0/host.star",
        "line": "45",
        "thread": "_destroy"
      },
      "stream": 0
    },
    {
      "timestamp": "2025-08-06T21:48:07.207821-04:00",
      "message": "",
      "attributes": {
        "col": "30",
        "filename": "sdk/0.3.0/host.star",
        "line": "45",
        "thread": "_destroy"
      },
      "stream": 0
    },
    {
      "timestamp": "2025-08-06T21:48:07.207848-04:00",
      "message": "\u001b[1m  # tls_private_key.vps\u001b[0m will be \u001b[1m\u001b[31mdestroyed\u001b[0m",
      "attributes": {
        "col": "30",
        "filename": "sdk/0.3.0/host.star",
        "line": "45",
        "thread": "_destroy"
      },
      "stream": 0
    },
    {
      "timestamp": "2025-08-06T21:48:07.207872-04:00",
      "message": "\u001b[0m  \u001b[31m-\u001b[0m\u001b[0m resource \"tls_private_key\" \"vps\" {",
      "attributes": {
        "col": "30",
        "filename": "sdk/0.3.0/host.star",
        "line": "45",
        "thread": "_destroy"
      },
      "stream": 0
    },
    {
      "timestamp": "2025-08-06T21:48:07.2079-04:00",
      "message": "      \u001b[31m-\u001b[0m\u001b[0m algorithm                     = \"RSA\" \u001b[90m-\u003e null\u001b[0m\u001b[0m",
      "attributes": {
        "col": "30",
        "filename": "sdk/0.3.0/host.star",
        "line": "45",
        "thread": "_destroy"
      },
      "stream": 0
    },
    {
      "timestamp": "2025-08-06T21:48:07.207924-04:00",
      "message": "      \u001b[31m-\u001b[0m\u001b[0m ecdsa_curve                   = \"P224\" \u001b[90m-\u003e null\u001b[0m\u001b[0m",
      "attributes": {
        "col": "30",
        "filename": "sdk/0.3.0/host.star",
        "line": "45",
        "thread": "_destroy"
      },
      "stream": 0
    },
    {
      "timestamp": "2025-08-06T21:48:07.207947-04:00",
      "message": "      \u001b[31m-\u001b[0m\u001b[0m id                            = \"2762a2f4a191df81ca88941ce1ef18994726db11\" \u001b[90m-\u003e null\u001b[0m\u001b[0m",
      "attributes": {
        "col": "30",
        "filename": "sdk/0.3.0/host.star",
        "line": "45",
        "thread": "_destroy"
      },
      "stream": 0
    },
    {
      "timestamp": "2025-08-06T21:48:07.207973-04:00",
      "message": "      \u001b[31m-\u001b[0m\u001b[0m private_key_openssh           = (sensitive value) \u001b[90m-\u003e null\u001b[0m\u001b[0m",
      "attributes": {
        "col": "30",
        "filename": "sdk/0.3.0/host.star",
        "line": "45",
        "thread": "_destroy"
      },
      "stream": 0
    },
    {
      "timestamp": "2025-08-06T21:48:07.207996-04:00",
      "message": "      \u001b[31m-\u001b[0m\u001b[0m private_key_pem               = (sensitive value) \u001b[90m-\u003e null\u001b[0m\u001b[0m",
      "attributes": {
        "col": "30",
        "filename": "sdk/0.3.0/host.star",
        "line": "45",
        "thread": "_destroy"
      },
      "stream": 0
    },
    {
      "timestamp": "2025-08-06T21:48:07.20802-04:00",
      "message": "      \u001b[31m-\u001b[0m\u001b[0m private_key_pem_pkcs8         = (sensitive value) \u001b[90m-\u003e null\u001b[0m\u001b[0m",
      "attributes": {
        "col": "30",
        "filename": "sdk/0.3.0/host.star",
        "line": "45",
        "thread": "_destroy"
      },
      "stream": 0
    },
    {
      "timestamp": "2025-08-06T21:48:07.208043-04:00",
      "message": "      \u001b[31m-\u001b[0m\u001b[0m public_key_fingerprint_md5    = \"0a:95:68:24:e9:6c:16:c5:80:35:c0:5b:e3:de:41:dd\" \u001b[90m-\u003e null\u001b[0m\u001b[0m",
      "attributes": {
        "col": "30",
        "filename": "sdk/0.3.0/host.star",
        "line": "45",
        "thread": "_destroy"
      },
      "stream": 0
    },
    {
      "timestamp": "2025-08-06T21:48:07.208065-04:00",
      "message": "      \u001b[31m-\u001b[0m\u001b[0m public_key_fingerprint_sha256 = \"SHA256:9ANKhjbDgDLdwK/MTc9joEYHPVkIVUAfNi/KhBUNCBs\" \u001b[90m-\u003e null\u001b[0m\u001b[0m",
      "attributes": {
        "col": "30",
        "filename": "sdk/0.3.0/host.star",
        "line": "45",
        "thread": "_destroy"
      },
      "stream": 0
    },
    {
      "timestamp": "2025-08-06T21:48:07.20809-04:00",
      "message": "      \u001b[31m-\u001b[0m\u001b[0m public_key_openssh            = \u003c\u003c-EOT",
      "attributes": {
        "col": "30",
        "filename": "sdk/0.3.0/host.star",
        "line": "45",
        "thread": "_destroy"
      },
      "stream": 0
    },
    {
      "timestamp": "2025-08-06T21:48:07.208112-04:00",
      "message": "            ssh-rsa AAAAB3NzaC1yc2EAAAADAQABAAACAQDcGu4ASieJhv9YkidDOahiwph1jwoJeYOuW2J/VTV2hrgRpR1Mb8V/6Gzc0As/HP6oVVqJzjekewy05O25ZdnximdarbSrnnAKGVnxyjSlyNxzOEqLhSZtp6cvC6t06AEaM4dj/JcpVwAApLY5JwQ3DPMMNpy73x08ZJdr3RXTOms7AICUB4TBmkbJSz2QojjPqdP95ocK5cJEnHF7GHSz7uH/V5Re2q9z3LPKunpoY0oUI2Tsg+JwIXqpiuydMHIdNzq1mNlmsstpMtp2X/eC38+0Ld61lP4bLUNuhtkzdSvwcIhm+1q0gt2XTS4NWkFEo3jDh42dCLT9L55f7mxMrrT4Crp1LrsoB5S7hefT/1u89iLTYVnMLaKCekhJUedEXyUBhUz3NUnuCUtS51eSnmZyKVctPhfhcxTSeYyZe8jF6LCTpaNkYyX638zLghC7QXz+nImU+JoAx3vAOfoCIvZPeX2YhLSTOePiNQ2YivoqOQ+fCIaPxLiO5VTXwUu8mc1BGdoEl/o0RZ0OIV1Ll30iB899Ik0l3KxVbmGc2TdrIPizpyX7O5TasYpm4mFteGBGYtwGDk/DY21+QzQbiYGSy/AGfYZWV3oN1xxr94tgDk4eyG5k2WhbamZeEGscQNySvZcd1yk8OBW+3j4xlLXSbhbqJPMgPXyOYzo7bQ==",
      "attributes": {
        "col": "30",
        "filename": "sdk/0.3.0/host.star",
        "line": "45",
        "thread": "_destroy"
      },
      "stream": 0
    },
    {
      "timestamp": "2025-08-06T21:48:07.208142-04:00",
      "message": "        EOT \u001b[90m-\u003e null\u001b[0m\u001b[0m",
      "attributes": {
        "col": "30",
        "filename": "sdk/0.3.0/host.star",
        "line": "45",
        "thread": "_destroy"
      },
      "stream": 0
    },
    {
      "timestamp": "2025-08-06T21:48:07.208164-04:00",
      "message": "      \u001b[31m-\u001b[0m\u001b[0m public_key_pem                = \u003c\u003c-EOT",
      "attributes": {
        "col": "30",
        "filename": "sdk/0.3.0/host.star",
        "line": "45",
        "thread": "_destroy"
      },
      "stream": 0
    },
    {
      "timestamp": "2025-08-06T21:48:07.208186-04:00",
      "message": "            -----BEGIN PUBLIC KEY-----",
      "attributes": {
        "col": "30",
        "filename": "sdk/0.3.0/host.star",
        "line": "45",
        "thread": "_destroy"
      },
      "stream": 0
    },
    {
      "timestamp": "2025-08-06T21:48:07.208211-04:00",
      "message": "            MIICIjANBgkqhkiG9w0BAQEFAAOCAg8AMIICCgKCAgEA3BruAEoniYb/WJInQzmo",
      "attributes": {
        "col": "30",
        "filename": "sdk/0.3.0/host.star",
        "line": "45",
        "thread": "_destroy"
      },
      "stream": 0
    },
    {
      "timestamp": "2025-08-06T21:48:07.208233-04:00",
      "message": "            YsKYdY8KCXmDrltif1U1doa4EaUdTG/Ff+hs3NALPxz+qFVaic43pHsMtOTtuWXZ",
      "attributes": {
        "col": "30",
        "filename": "sdk/0.3.0/host.star",
        "line": "45",
        "thread": "_destroy"
      },
      "stream": 0
    },
    {
      "timestamp": "2025-08-06T21:48:07.208258-04:00",
      "message": "            8YpnWq20q55wChlZ8co0pcjcczhKi4UmbaenLwurdOgBGjOHY/yXKVcAAKS2OScE",
      "attributes": {
        "col": "30",
        "filename": "sdk/0.3.0/host.star",
        "line": "45",
        "thread": "_destroy"
      },
      "stream": 0
    },
    {
      "timestamp": "2025-08-06T21:48:07.20828-04:00",
      "message": "            NwzzDDacu98dPGSXa90V0zprOwCAlAeEwZpGyUs9kKI4z6nT/eaHCuXCRJxxexh0",
      "attributes": {
        "col": "30",
        "filename": "sdk/0.3.0/host.star",
        "line": "45",
        "thread": "_destroy"
      },
      "stream": 0
    },
    {
      "timestamp": "2025-08-06T21:48:07.208305-04:00",
      "message": "            s+7h/1eUXtqvc9yzyrp6aGNKFCNk7IPicCF6qYrsnTByHTc6tZjZZrLLaTLadl/3",
      "attributes": {
        "col": "30",
        "filename": "sdk/0.3.0/host.star",
        "line": "45",
        "thread": "_destroy"
      },
      "stream": 0
    },
    {
      "timestamp": "2025-08-06T21:48:07.208327-04:00",
      "message": "            gt/PtC3etZT+Gy1DbobZM3Ur8HCIZvtatILdl00uDVpBRKN4w4eNnQi0/S+eX+5s",
      "attributes": {
        "col": "30",
        "filename": "sdk/0.3.0/host.star",
        "line": "45",
        "thread": "_destroy"
      },
      "stream": 0
    },
    {
      "timestamp": "2025-08-06T21:48:07.208348-04:00",
      "message": "            TK60+Aq6dS67KAeUu4Xn0/9bvPYi02FZzC2ignpISVHnRF8lAYVM9zVJ7glLUudX",
      "attributes": {
        "col": "30",
        "filename": "sdk/0.3.0/host.star",
        "line": "45",
        "thread": "_destroy"
      },
      "stream": 0
    },
    {
      "timestamp": "2025-08-06T21:48:07.20838-04:00",
      "message": "            kp5mcilXLT4X4XMU0nmMmXvIxeiwk6WjZGMl+t/My4IQu0F8/pyJlPiaAMd7wDn6",
      "attributes": {
        "col": "30",
        "filename": "sdk/0.3.0/host.star",
        "line": "45",
        "thread": "_destroy"
      },
      "stream": 0
    },
    {
      "timestamp": "2025-08-06T21:48:07.208403-04:00",
      "message": "            AiL2T3l9mIS0kznj4jUNmIr6KjkPnwiGj8S4juVU18FLvJnNQRnaBJf6NEWdDiFd",
      "attributes": {
        "col": "30",
        "filename": "sdk/0.3.0/host.star",
        "line": "45",
        "thread": "_destroy"
      },
      "stream": 0
    },
    {
      "timestamp": "2025-08-06T21:48:07.208426-04:00",
      "message": "            S5d9IgfPfSJNJdysVW5hnNk3ayD4s6cl+zuU2rGKZuJhbXhgRmLcBg5Pw2NtfkM0",
      "attributes": {
        "col": "30",
        "filename": "sdk/0.3.0/host.star",
        "line": "45",
        "thread": "_destroy"
      },
      "stream": 0
    },
    {
      "timestamp": "2025-08-06T21:48:07.208448-04:00",
      "message": "            G4mBksvwBn2GVld6Ddcca/eLYA5OHshuZNloW2pmXhBrHEDckr2XHdcpPDgVvt4+",
      "attributes": {
        "col": "30",
        "filename": "sdk/0.3.0/host.star",
        "line": "45",
        "thread": "_destroy"
      },
      "stream": 0
    },
    {
      "timestamp": "2025-08-06T21:48:07.208469-04:00",
      "message": "            MZS10m4W6iTzID18jmM6O20CAwEAAQ==",
      "attributes": {
        "col": "30",
        "filename": "sdk/0.3.0/host.star",
        "line": "45",
        "thread": "_destroy"
      },
      "stream": 0
    },
    {
      "timestamp": "2025-08-06T21:48:07.208491-04:00",
      "message": "            -----END PUBLIC KEY-----",
      "attributes": {
        "col": "30",
        "filename": "sdk/0.3.0/host.star",
        "line": "45",
        "thread": "_destroy"
      },
      "stream": 0
    },
    {
      "timestamp": "2025-08-06T21:48:07.208512-04:00",
      "message": "        EOT \u001b[90m-\u003e null\u001b[0m\u001b[0m",
      "attributes": {
        "col": "30",
        "filename": "sdk/0.3.0/host.star",
        "line": "45",
        "thread": "_destroy"
      },
      "stream": 0
    },
    {
      "timestamp": "2025-08-06T21:48:07.208537-04:00",
      "message": "      \u001b[31m-\u001b[0m\u001b[0m rsa_bits                      = 4096 \u001b[90m-\u003e null\u001b[0m\u001b[0m",
      "attributes": {
        "col": "30",
        "filename": "sdk/0.3.0/host.star",
        "line": "45",
        "thread": "_destroy"
      },
      "stream": 0
    },
    {
      "timestamp": "2025-08-06T21:48:07.208561-04:00",
      "message": "    }",
      "attributes": {
        "col": "30",
        "filename": "sdk/0.3.0/host.star",
        "line": "45",
        "thread": "_destroy"
      },
      "stream": 0
    },
    {
      "timestamp": "2025-08-06T21:48:07.208583-04:00",
      "message": "",
      "attributes": {
        "col": "30",
        "filename": "sdk/0.3.0/host.star",
        "line": "45",
        "thread": "_destroy"
      },
      "stream": 0
    },
    {
      "timestamp": "2025-08-06T21:48:07.208605-04:00",
      "message": "\u001b[1mPlan:\u001b[0m 0 to add, 0 to change, 3 to destroy.",
      "attributes": {
        "col": "30",
        "filename": "sdk/0.3.0/host.star",
        "line": "45",
        "thread": "_destroy"
      },
      "stream": 0
    },
    {
      "timestamp": "2025-08-06T21:48:07.208627-04:00",
      "message": "\u001b[0m",
      "attributes": {
        "col": "30",
        "filename": "sdk/0.3.0/host.star",
        "line": "45",
        "thread": "_destroy"
      },
      "stream": 0
    },
    {
      "timestamp": "2025-08-06T21:48:07.20865-04:00",
      "message": "Changes to Outputs:",
      "attributes": {
        "col": "30",
        "filename": "sdk/0.3.0/host.star",
        "line": "45",
        "thread": "_destroy"
      },
      "stream": 0
    },
    {
      "timestamp": "2025-08-06T21:48:07.208674-04:00",
      "message": "  \u001b[31m-\u001b[0m\u001b[0m ip          = \"162.243.84.176\" \u001b[90m-\u003e null\u001b[0m\u001b[0m",
      "attributes": {
        "col": "30",
        "filename": "sdk/0.3.0/host.star",
        "line": "45",
        "thread": "_destroy"
      },
      "stream": 0
    },
    {
      "timestamp": "2025-08-06T21:48:07.208699-04:00",
      "message": "  \u001b[31m-\u001b[0m\u001b[0m private_key = (sensitive value) \u001b[90m-\u003e null\u001b[0m\u001b[0m",
      "attributes": {
        "col": "30",
        "filename": "sdk/0.3.0/host.star",
        "line": "45",
        "thread": "_destroy"
      },
      "stream": 0
    },
    {
      "timestamp": "2025-08-06T21:48:07.208724-04:00",
      "message": "  \u001b[31m-\u001b[0m\u001b[0m public_key  = \u003c\u003c-EOT",
      "attributes": {
        "col": "30",
        "filename": "sdk/0.3.0/host.star",
        "line": "45",
        "thread": "_destroy"
      },
      "stream": 0
    },
    {
      "timestamp": "2025-08-06T21:48:07.208748-04:00",
      "message": "        ssh-rsa AAAAB3NzaC1yc2EAAAADAQABAAACAQDcGu4ASieJhv9YkidDOahiwph1jwoJeYOuW2J/VTV2hrgRpR1Mb8V/6Gzc0As/HP6oVVqJzjekewy05O25ZdnximdarbSrnnAKGVnxyjSlyNxzOEqLhSZtp6cvC6t06AEaM4dj/JcpVwAApLY5JwQ3DPMMNpy73x08ZJdr3RXTOms7AICUB4TBmkbJSz2QojjPqdP95ocK5cJEnHF7GHSz7uH/V5Re2q9z3LPKunpoY0oUI2Tsg+JwIXqpiuydMHIdNzq1mNlmsstpMtp2X/eC38+0Ld61lP4bLUNuhtkzdSvwcIhm+1q0gt2XTS4NWkFEo3jDh42dCLT9L55f7mxMrrT4Crp1LrsoB5S7hefT/1u89iLTYVnMLaKCekhJUedEXyUBhUz3NUnuCUtS51eSnmZyKVctPhfhcxTSeYyZe8jF6LCTpaNkYyX638zLghC7QXz+nImU+JoAx3vAOfoCIvZPeX2YhLSTOePiNQ2YivoqOQ+fCIaPxLiO5VTXwUu8mc1BGdoEl/o0RZ0OIV1Ll30iB899Ik0l3KxVbmGc2TdrIPizpyX7O5TasYpm4mFteGBGYtwGDk/DY21+QzQbiYGSy/AGfYZWV3oN1xxr94tgDk4eyG5k2WhbamZeEGscQNySvZcd1yk8OBW+3j4xlLXSbhbqJPMgPXyOYzo7bQ==",
      "attributes": {
        "col": "30",
        "filename": "sdk/0.3.0/host.star",
        "line": "45",
        "thread": "_destroy"
      },
      "stream": 0
    },
    {
      "timestamp": "2025-08-06T21:48:07.208785-04:00",
      "message": "    EOT \u001b[90m-\u003e null\u001b[0m\u001b[0m",
      "attributes": {
        "col": "30",
        "filename": "sdk/0.3.0/host.star",
        "line": "45",
        "thread": "_destroy"
      },
      "stream": 0
    },
    {
      "timestamp": "2025-08-06T21:48:07.262509-04:00",
      "message": "\u001b[0m\u001b[1mdigitalocean_droplet.vps: Destroying... [id=512034846]\u001b[0m\u001b[0m",
      "attributes": {
        "col": "30",
        "filename": "sdk/0.3.0/host.star",
        "line": "45",
        "thread": "_destroy"
      },
      "stream": 0
    },
    {
      "timestamp": "2025-08-06T21:48:17.267889-04:00",
      "message": "\u001b[0m\u001b[1mdigitalocean_droplet.vps: Still destroying... [id=512034846, 10s elapsed]\u001b[0m\u001b[0m",
      "attributes": {
        "col": "30",
        "filename": "sdk/0.3.0/host.star",
        "line": "45",
        "thread": "_destroy"
      },
      "stream": 0
    },
    {
      "timestamp": "2025-08-06T21:48:27.268435-04:00",
      "message": "\u001b[0m\u001b[1mdigitalocean_droplet.vps: Still destroying... [id=512034846, 20s elapsed]\u001b[0m\u001b[0m",
      "attributes": {
        "col": "30",
        "filename": "sdk/0.3.0/host.star",
        "line": "45",
        "thread": "_destroy"
      },
      "stream": 0
    },
    {
      "timestamp": "2025-08-06T21:48:29.113118-04:00",
      "message": "\u001b[0m\u001b[1mdigitalocean_droplet.vps: Destruction complete after 22s\u001b[0m",
      "attributes": {
        "col": "30",
        "filename": "sdk/0.3.0/host.star",
        "line": "45",
        "thread": "_destroy"
      },
      "stream": 0
    },
    {
      "timestamp": "2025-08-06T21:48:29.114401-04:00",
      "message": "\u001b[0m\u001b[1mdigitalocean_ssh_key.default: Destroying... [id=49770501]\u001b[0m\u001b[0m",
      "attributes": {
        "col": "30",
        "filename": "sdk/0.3.0/host.star",
        "line": "45",
        "thread": "_destroy"
      },
      "stream": 0
    },
    {
      "timestamp": "2025-08-06T21:48:29.366237-04:00",
      "message": "\u001b[0m\u001b[1mdigitalocean_ssh_key.default: Destruction complete after 0s\u001b[0m",
      "attributes": {
        "col": "30",
        "filename": "sdk/0.3.0/host.star",
        "line": "45",
        "thread": "_destroy"
      },
      "stream": 0
    },
    {
      "timestamp": "2025-08-06T21:48:29.376034-04:00",
      "message": "\u001b[0m\u001b[1mtls_private_key.vps: Destroying... [id=2762a2f4a191df81ca88941ce1ef18994726db11]\u001b[0m\u001b[0m",
      "attributes": {
        "col": "30",
        "filename": "sdk/0.3.0/host.star",
        "line": "45",
        "thread": "_destroy"
      },
      "stream": 0
    },
    {
      "timestamp": "2025-08-06T21:48:29.377216-04:00",
      "message": "\u001b[0m\u001b[1mtls_private_key.vps: Destruction complete after 0s\u001b[0m",
      "attributes": {
        "col": "30",
        "filename": "sdk/0.3.0/host.star",
        "line": "45",
        "thread": "_destroy"
      },
      "stream": 0
    },
    {
      "timestamp": "2025-08-06T21:48:29.808757-04:00",
      "message": "\u001b[0m\u001b[1m\u001b[32m",
      "attributes": {
        "col": "30",
        "filename": "sdk/0.3.0/host.star",
        "line": "45",
        "thread": "_destroy"
      },
      "stream": 0
    },
    {
      "timestamp": "2025-08-06T21:48:29.808838-04:00",
      "message": "Destroy complete! Resources: 3 destroyed.",
      "attributes": {
        "col": "30",
        "filename": "sdk/0.3.0/host.star",
        "line": "45",
        "thread": "_destroy"
      },
      "stream": 0
    },
    {
      "timestamp": "2025-08-06T21:48:29.808868-04:00",
      "message": "\u001b[0m",
      "attributes": {
        "col": "30",
        "filename": "sdk/0.3.0/host.star",
        "line": "45",
        "thread": "_destroy"
      },
      "stream": 0
    },
    {
      "timestamp": "2025-08-06T21:48:30.436609-04:00",
      "message": "Failed to delete secret",
      "attributes": {
        "col": "14",
        "filename": "release.ocu.star",
        "line": "63",
        "thread": "_destroy"
      },
      "stream": 0
    },
    {
      "timestamp": "2025-08-06T21:48:30.436766-04:00",
      "message": "Unable to complete your delete request\n",
      "attributes": {
        "col": "14",
        "filename": "release.ocu.star",
        "line": "64",
        "thread": "_destroy"
      },
      "stream": 0
    }
  ]
}