{
  "kind": "ref",
  "body_type": "release.FunctionState",
  "body": {
    "current": {
      "id": "1",
      "fn": {
        "name": "_destroy",
        "pos": "release.ocu.star:53:1"
      },
      "status": "running",
      "inputs": {
        "environment": {
          "ref": "@/environment/staging",
          "value": {
            "attributes": {
              "infisical_env": "staging",
              "type": "staging"
            },
            "name": "staging"
          }
        }
      }
    },
    "history": [
      {
        "time": "2025-08-06T21:49:25.957276-04:00",
        "status": "running"
      }
    ]
  }
}